ordered_namespace/__init__.py
ordered_namespace/core.py
ordered_namespace-2019.6.8.dist-info/LICENSE
ordered_namespace-2019.6.8.dist-info/METADATA
ordered_namespace-2019.6.8.dist-info/WHEEL
ordered_namespace-2019.6.8.dist-info/top_level.txt
ordered_namespace-2019.6.8.dist-info/RECORD
